foxyNN/__init__.py
foxyNN/lossfuncs.py
foxyNN/tools.py
foxyNN-1.0.0.dist-info/LICENSE
foxyNN-1.0.0.dist-info/METADATA
foxyNN-1.0.0.dist-info/WHEEL
foxyNN-1.0.0.dist-info/top_level.txt
foxyNN-1.0.0.dist-info/RECORD
